aicooking_ble/__init__.py
aicooking_ble/parser.py
aicooking_ble/py.typed
aicooking_ble-0.1.2.dist-info/LICENSE
aicooking_ble-0.1.2.dist-info/WHEEL
aicooking_ble-0.1.2.dist-info/METADATA
aicooking_ble-0.1.2.dist-info/RECORD
